spitfire/__init__.py
spitfire/test_util.py
spitfire/text.py
spitfire/compiler/__init__.py
spitfire/compiler/analyzer.py
spitfire/compiler/analyzer.py.bak
spitfire/compiler/analyzer_test.py
spitfire/compiler/ast.py
spitfire/compiler/ast.py.bak
spitfire/compiler/codegen.py
spitfire/compiler/codegen.py.bak
spitfire/compiler/compiler.py
spitfire/compiler/compiler.py.bak
spitfire/compiler/optimizer.py
spitfire/compiler/optimizer.py.bak
spitfire/compiler/optimizer_test.py
spitfire/compiler/options.py
spitfire/compiler/options.py.bak
spitfire/compiler/parser.g
spitfire/compiler/parser.py.bak
spitfire/compiler/parser_test.py
spitfire/compiler/scanner.py
spitfire/compiler/util.py
spitfire/compiler/util.py.bak
spitfire/compiler/visitor.py
spitfire/compiler/visitor.py.bak
spitfire/compiler/walker.py
spitfire/compiler/walker.py.bak
spitfire/compiler/xhtml2ast.py
spitfire/compiler/xhtml2ast.py.bak
spitfire/compiler/macros/__init__.py
spitfire/compiler/macros/i18n.py
spitfire/compiler/macros/i18n.py.bak
spitfire/runtime/__init__.py
spitfire/runtime/__init__.py.bak
spitfire/runtime/baked.py
spitfire/runtime/baked_test.py
spitfire/runtime/filters.py
spitfire/runtime/filters.py.bak
spitfire/runtime/repeater.py
spitfire/runtime/repeater.py.bak
spitfire/runtime/runner.py
spitfire/runtime/runner.py.bak
spitfire/runtime/template.py
spitfire/runtime/template.py.bak
spitfire/runtime/template_test.py
spitfire/runtime/udn.py
spitfire/runtime/udn.py.bak
spitfire/runtime/udn_test.py
spitfire3-0.7.15.dist-info/LICENSE
spitfire3-0.7.15.dist-info/WHEEL
spitfire3-0.7.15.dist-info/METADATA
spitfire3-0.7.15.dist-info/RECORD
