Metadata-Version: 2.1
Name: spitfire3
Version: 0.7.15
Summary: Spitfire fork for Python3
Author: Nafi Amaan Hossain
Classifier: License :: OSI Approved :: MIT License
